owl/__init__.py
owl/detection/__init__.py
owl/detection/detectors.py
owl/utils/__init__.py
owl/utils/algorithms.py
owl/utils/config.py
owl/utils/image.py
owl/utils/io.py
owl/viz/__init__.py
owl/viz/media.py
openweedlocator_tools-0.0.2.dist-info/LICENSE
openweedlocator_tools-0.0.2.dist-info/METADATA
openweedlocator_tools-0.0.2.dist-info/WHEEL
openweedlocator_tools-0.0.2.dist-info/top_level.txt
openweedlocator_tools-0.0.2.dist-info/RECORD
