Metadata-Version: 2.1
Name: openweedlocator-tools
Version: 0.0.2
Summary: A toolkit for green-on-brown and green-on-green weed detection
Home-page: https://github.com/geezacoleman/openweedlocator-tools
Author: Guy Coleman
Author-email: hoot@openweedlocator.com
Maintainer-email: guy.coleman@sydney.edu.au
License: MIT
Classifier: Programming Language :: Python :: 3
Classifier: License :: OSI Approved :: MIT License
Classifier: Operating System :: OS Independent
License-File: LICENSE
Requires-Dist: imutils <1.0,>=0.5
Requires-Dist: numpy <2.0,>=1.10
Requires-Dist: pandas >2.0
Requires-Dist: python-dateutil <3.0,>=2.8
Provides-Extra: desktop
Requires-Dist: ultralytics ; extra == 'desktop'
Requires-Dist: opencv-contrib-python <5.0,>=4.0 ; extra == 'desktop'
Requires-Dist: opencv-python <5.0,>=4.0 ; extra == 'desktop'
Provides-Extra: rpi
Requires-Dist: opencv-contrib-python <5.0,>=4.0 ; extra == 'rpi'
Requires-Dist: opencv-python <5.0,>=4.0 ; extra == 'rpi'
